altgosling/__init__.py
altgosling/static/widget.js
altgosling-0.0.0.dist-info/METADATA
altgosling-0.0.0.dist-info/WHEEL
altgosling-0.0.0.dist-info/RECORD
