Metadata-Version: 2.4
Name: altgosling
Version: 0.0.0
Requires-Dist: anywidget
Provides-Extra: dev
Requires-Dist: jupyterlab; extra == 'dev'
Requires-Dist: watchfiles; extra == 'dev'
